{
  "version": "2.5.0",
  "summary": {
    "title": "Threat Model - Admin",
    "owner": "Faris Aryaputra",
    "description": "Threat Model DFD Level 1",
    "id": 0
  },
  "detail": {
    "contributors": [],
    "diagrams": [
      {
        "id": 0,
        "title": "Admin",
        "diagramType": "STRIDE",
        "placeholder": "New STRIDE diagram description",
        "thumbnail": "./public/content/images/thumbnail.stride.jpg",
        "version": "2.5.0",
        "cells": [
          {
            "position": {
              "x": 180,
              "y": 120
            },
            "size": {
              "width": 112.5,
              "height": 60
            },
            "attrs": {
              "text": {
                "text": "admin"
              },
              "body": {
                "stroke": "red",
                "strokeWidth": 2.5,
                "strokeDasharray": null
              }
            },
            "visible": true,
            "shape": "actor",
            "zIndex": 1,
            "ports": {
              "groups": {
                "top": {
                  "position": "top",
                  "attrs": {
                    "circle": {
                      "r": 4,
                      "magnet": true,
                      "stroke": "#5F95FF",
                      "strokeWidth": 1,
                      "fill": "#fff",
                      "style": {
                        "visibility": "hidden"
                      }
                    }
                  }
                },
                "right": {
                  "position": "right",
                  "attrs": {
                    "circle": {
                      "r": 4,
                      "magnet": true,
                      "stroke": "#5F95FF",
                      "strokeWidth": 1,
                      "fill": "#fff",
                      "style": {
                        "visibility": "hidden"
                      }
                    }
                  }
                },
                "bottom": {
                  "position": "bottom",
                  "attrs": {
                    "circle": {
                      "r": 4,
                      "magnet": true,
                      "stroke": "#5F95FF",
                      "strokeWidth": 1,
                      "fill": "#fff",
                      "style": {
                        "visibility": "hidden"
                      }
                    }
                  }
                },
                "left": {
                  "position": "left",
                  "attrs": {
                    "circle": {
                      "r": 4,
                      "magnet": true,
                      "stroke": "#5F95FF",
                      "strokeWidth": 1,
                      "fill": "#fff",
                      "style": {
                        "visibility": "hidden"
                      }
                    }
                  }
                }
              },
              "items": [
                {
                  "group": "top",
                  "id": "5636e0c7-ca05-4fd4-b747-5d7b3e167ba2"
                },
                {
                  "group": "right",
                  "id": "d2c770db-d486-4430-9a71-fcdd8f29e3c9"
                },
                {
                  "group": "bottom",
                  "id": "8a2cd1be-df48-4bd2-ab93-67b32fa6dbb7"
                },
                {
                  "group": "left",
                  "id": "59f7b04f-94f9-4e8b-8668-0dddaa73f93d"
                }
              ]
            },
            "id": "900a8068-0408-420e-a74c-2bc2b2107088",
            "data": {
              "type": "tm.Actor",
              "name": "admin",
              "description": "",
              "isTrustBoundary": false,
              "outOfScope": false,
              "reasonOutOfScope": "",
              "hasOpenThreats": true,
              "providesAuthentication": false,
              "threats": [
                {
                  "id": "85074c67-5308-4bd7-9828-ff8c224f04b3",
                  "title": "Penyerang menyamar sebagai admin",
                  "status": "Open",
                  "severity": "Critical",
                  "type": "Spoofing",
                  "description": "Kontrol penuh sistem,",
                  "mitigation": "RBAC",
                  "modelType": "STRIDE",
                  "new": false,
                  "number": 1,
                  "score": "20"
                },
                {
                  "id": "5e0ab09b-cb37-432e-9439-487547209c38",
                  "title": "Admin menyangkal perubahan akun",
                  "status": "Open",
                  "severity": "Medium",
                  "type": "Repudiation",
                  "description": "Berdampak pada Tidak ada bukti forensik ketika admin melakukan perubahan",
                  "mitigation": "Audit log, timestamp, immutable log, blockchain",
                  "modelType": "STRIDE",
                  "new": false,
                  "number": 2,
                  "score": "9"
                }
              ],
              "threatFrequency": {
                "spoofing": 2,
                "repudiation": 2
              }
            }
          },
          {
            "position": {
              "x": 445,
              "y": 10
            },
            "size": {
              "width": 120,
              "height": 110
            },
            "attrs": {
              "text": {
                "text": "Mengelola\nakun User"
              },
              "body": {
                "stroke": "red",
                "strokeWidth": 2.5,
                "strokeDasharray": null
              }
            },
            "visible": true,
            "shape": "process",
            "zIndex": 2,
            "ports": {
              "groups": {
                "top": {
                  "position": "top",
                  "attrs": {
                    "circle": {
                      "r": 4,
                      "magnet": true,
                      "stroke": "#5F95FF",
                      "strokeWidth": 1,
                      "fill": "#fff",
                      "style": {
                        "visibility": "hidden"
                      }
                    }
                  }
                },
                "right": {
                  "position": "right",
                  "attrs": {
                    "circle": {
                      "r": 4,
                      "magnet": true,
                      "stroke": "#5F95FF",
                      "strokeWidth": 1,
                      "fill": "#fff",
                      "style": {
                        "visibility": "hidden"
                      }
                    }
                  }
                },
                "bottom": {
                  "position": "bottom",
                  "attrs": {
                    "circle": {
                      "r": 4,
                      "magnet": true,
                      "stroke": "#5F95FF",
                      "strokeWidth": 1,
                      "fill": "#fff",
                      "style": {
                        "visibility": "hidden"
                      }
                    }
                  }
                },
                "left": {
                  "position": "left",
                  "attrs": {
                    "circle": {
                      "r": 4,
                      "magnet": true,
                      "stroke": "#5F95FF",
                      "strokeWidth": 1,
                      "fill": "#fff",
                      "style": {
                        "visibility": "hidden"
                      }
                    }
                  }
                }
              },
              "items": [
                {
                  "group": "top",
                  "id": "e925dc40-2557-476d-9f4a-e1cc4b7b1d26"
                },
                {
                  "group": "right",
                  "id": "dfc0c767-59d3-49d6-b7ec-a03be9cde179"
                },
                {
                  "group": "bottom",
                  "id": "473134c5-35c1-4c4e-9652-c0cff5255eab"
                },
                {
                  "group": "left",
                  "id": "5e7f6726-db15-4b09-aff0-519a60b28048"
                }
              ]
            },
            "id": "235b1b15-4644-4e49-9843-f013b160a0b9",
            "data": {
              "type": "tm.Process",
              "name": "Mengelola\nakun User",
              "description": "",
              "outOfScope": false,
              "isTrustBoundary": false,
              "reasonOutOfScope": "",
              "hasOpenThreats": true,
              "handlesCardPayment": false,
              "handlesGoodsOrServices": false,
              "isWebApplication": false,
              "privilegeLevel": "",
              "threats": [
                {
                  "id": "bd22045a-6f3e-471c-ac3d-ceb1cc6d9743",
                  "title": "Manipulasi Role",
                  "status": "Open",
                  "severity": "High",
                  "type": "Tampering",
                  "description": "Eskalasi Hak Akses",
                  "mitigation": "Input Validation",
                  "modelType": "STRIDE",
                  "new": false,
                  "number": 9,
                  "score": "16"
                },
                {
                  "id": "28cada69-7c4f-4eba-8095-adbb2bf61d6a",
                  "title": "Aksi admin tidak dapat dilacak",
                  "status": "Open",
                  "severity": "Medium",
                  "type": "Repudiation",
                  "description": "Forensik Gagal",
                  "mitigation": "Audit Trail",
                  "modelType": "STRIDE",
                  "new": false,
                  "number": 10,
                  "score": "9"
                },
                {
                  "id": "7a91c6b8-3c27-407e-8742-621fcbeff640",
                  "title": "Role User dimanipulasi",
                  "status": "Open",
                  "severity": "Critical",
                  "type": "Elevation of privilege",
                  "description": "Kontrol sistem bocor",
                  "mitigation": "RBAC",
                  "modelType": "STRIDE",
                  "new": false,
                  "number": 11,
                  "score": "20"
                }
              ],
              "threatFrequency": {
                "spoofing": 0,
                "tampering": 1,
                "repudiation": 1,
                "informationDisclosure": 0,
                "denialOfService": 0,
                "elevationOfPrivilege": 1
              }
            }
          },
          {
            "position": {
              "x": 450,
              "y": 179.99999999999991
            },
            "size": {
              "width": 110,
              "height": 120
            },
            "attrs": {
              "text": {
                "text": "Melihat Audit\n& Auth Log"
              },
              "body": {
                "stroke": "red",
                "strokeWidth": 2.5,
                "strokeDasharray": null
              }
            },
            "visible": true,
            "shape": "process",
            "zIndex": 3,
            "ports": {
              "groups": {
                "top": {
                  "position": "top",
                  "attrs": {
                    "circle": {
                      "r": 4,
                      "magnet": true,
                      "stroke": "#5F95FF",
                      "strokeWidth": 1,
                      "fill": "#fff",
                      "style": {
                        "visibility": "hidden"
                      }
                    }
                  }
                },
                "right": {
                  "position": "right",
                  "attrs": {
                    "circle": {
                      "r": 4,
                      "magnet": true,
                      "stroke": "#5F95FF",
                      "strokeWidth": 1,
                      "fill": "#fff",
                      "style": {
                        "visibility": "hidden"
                      }
                    }
                  }
                },
                "bottom": {
                  "position": "bottom",
                  "attrs": {
                    "circle": {
                      "r": 4,
                      "magnet": true,
                      "stroke": "#5F95FF",
                      "strokeWidth": 1,
                      "fill": "#fff",
                      "style": {
                        "visibility": "hidden"
                      }
                    }
                  }
                },
                "left": {
                  "position": "left",
                  "attrs": {
                    "circle": {
                      "r": 4,
                      "magnet": true,
                      "stroke": "#5F95FF",
                      "strokeWidth": 1,
                      "fill": "#fff",
                      "style": {
                        "visibility": "hidden"
                      }
                    }
                  }
                }
              },
              "items": [
                {
                  "group": "top",
                  "id": "e925dc40-2557-476d-9f4a-e1cc4b7b1d26"
                },
                {
                  "group": "right",
                  "id": "dfc0c767-59d3-49d6-b7ec-a03be9cde179"
                },
                {
                  "group": "bottom",
                  "id": "473134c5-35c1-4c4e-9652-c0cff5255eab"
                },
                {
                  "group": "left",
                  "id": "5e7f6726-db15-4b09-aff0-519a60b28048"
                }
              ]
            },
            "id": "8670885f-53e7-4d99-b8e5-7137939c668c",
            "data": {
              "type": "tm.Process",
              "name": "Melihat Audit\n& Auth Log",
              "description": "",
              "outOfScope": false,
              "isTrustBoundary": false,
              "reasonOutOfScope": "",
              "hasOpenThreats": true,
              "handlesCardPayment": false,
              "handlesGoodsOrServices": false,
              "isWebApplication": false,
              "privilegeLevel": "",
              "threats": [
                {
                  "id": "03c4034e-46ec-4888-a742-fbcdc7cca9c9",
                  "title": "Audit log diakses pihak tak berwenang",
                  "status": "Open",
                  "severity": "High",
                  "type": "Information disclosure",
                  "description": "Kebocoran data sensitif",
                  "mitigation": "Access control, masking data",
                  "modelType": "STRIDE",
                  "new": false,
                  "number": 3,
                  "score": ""
                },
                {
                  "id": "82912d7e-8cef-41fc-9c6d-9bbf8b2f9f74",
                  "title": "Query log berlebihan",
                  "status": "Open",
                  "severity": "Medium",
                  "type": "Denial of service",
                  "description": "Sistem admin lambat/tidak responsif",
                  "mitigation": "Rate limiting, pagination",
                  "modelType": "STRIDE",
                  "new": false,
                  "number": 4,
                  "score": ""
                }
              ],
              "threatFrequency": {
                "spoofing": 0,
                "tampering": 0,
                "repudiation": 0,
                "informationDisclosure": 1,
                "denialOfService": 1,
                "elevationOfPrivilege": 0
              }
            }
          },
          {
            "shape": "flow",
            "attrs": {
              "line": {
                "stroke": "red",
                "strokeWidth": 2.5,
                "targetMarker": {
                  "name": "block"
                },
                "sourceMarker": {
                  "name": ""
                },
                "strokeDasharray": null
              }
            },
            "width": 200,
            "height": 100,
            "zIndex": 10,
            "connector": "smooth",
            "data": {
              "type": "tm.Flow",
              "name": "Data Flow",
              "description": "",
              "outOfScope": false,
              "isTrustBoundary": false,
              "reasonOutOfScope": "",
              "hasOpenThreats": true,
              "isBidirectional": false,
              "isEncrypted": false,
              "isPublicNetwork": false,
              "protocol": "",
              "threats": [
                {
                  "id": "236edc4f-b83d-4c8c-8c6d-caafb6182666",
                  "title": "Data akun diubah saat transit",
                  "status": "Open",
                  "severity": "High",
                  "type": "Tampering",
                  "description": "Role salah tersimpan",
                  "mitigation": "integrity check",
                  "modelType": "STRIDE",
                  "new": false,
                  "number": 5,
                  "score": ""
                },
                {
                  "id": "d270fcd3-7353-4516-87a3-3ca1186de55d",
                  "title": "Data akun disadap",
                  "status": "Open",
                  "severity": "High",
                  "type": "Information disclosure",
                  "description": "Kebocoran kredensial",
                  "mitigation": "Enkripsi in-transit, memperkuat kemanan jaringan lokal",
                  "modelType": "STRIDE",
                  "new": false,
                  "number": 6,
                  "score": ""
                }
              ],
              "trustBoundaryIds": [],
              "threatFrequency": {
                "tampering": 1,
                "informationDisclosure": 1,
                "denialOfService": 0
              }
            },
            "labels": [
              "Data Flow"
            ],
            "id": "bc463654-9cea-41a4-a395-6ebbf2ef99bb",
            "source": {
              "x": 290,
              "y": 150
            },
            "target": {
              "cell": "235b1b15-4644-4e49-9843-f013b160a0b9",
              "port": "5e7f6726-db15-4b09-aff0-519a60b28048"
            },
            "vertices": [
              {
                "x": 310,
                "y": 150
              },
              {
                "x": 340,
                "y": 110
              },
              {
                "x": 390,
                "y": 65
              }
            ]
          },
          {
            "shape": "flow",
            "attrs": {
              "line": {
                "stroke": "red",
                "strokeWidth": 2.5,
                "targetMarker": {
                  "name": "block"
                },
                "sourceMarker": {
                  "name": ""
                },
                "strokeDasharray": null
              }
            },
            "width": 200,
            "height": 100,
            "zIndex": 10,
            "connector": "smooth",
            "data": {
              "type": "tm.Flow",
              "name": "Data Flow",
              "description": "",
              "outOfScope": false,
              "isTrustBoundary": false,
              "reasonOutOfScope": "",
              "hasOpenThreats": true,
              "isBidirectional": false,
              "isEncrypted": false,
              "isPublicNetwork": false,
              "protocol": "",
              "threats": [
                {
                  "id": "b1a94660-c0e8-4ad7-bc5d-5fadd267972c",
                  "title": "Audit log bocor saat transmisi",
                  "status": "Open",
                  "severity": "Medium",
                  "type": "Information disclosure",
                  "description": "Ekspos aktivitas sistem",
                  "mitigation": "Enkripsi komunikasi",
                  "modelType": "STRIDE",
                  "new": false,
                  "number": 7,
                  "score": "12"
                }
              ],
              "trustBoundaryIds": [],
              "threatFrequency": {
                "tampering": 0,
                "informationDisclosure": 2,
                "denialOfService": 0
              }
            },
            "labels": [
              "Data Flow"
            ],
            "id": "c2bc3c6f-ad33-430d-9301-d4e88042da4c",
            "source": {
              "x": 293,
              "y": 157
            },
            "target": {
              "cell": "8670885f-53e7-4d99-b8e5-7137939c668c",
              "port": "5e7f6726-db15-4b09-aff0-519a60b28048"
            },
            "vertices": [
              {
                "x": 370,
                "y": 200
              },
              {
                "x": 390,
                "y": 220
              }
            ]
          },
          {
            "shape": "flow",
            "attrs": {
              "line": {
                "stroke": "#333333",
                "targetMarker": {
                  "name": "block"
                },
                "sourceMarker": {
                  "name": ""
                },
                "strokeDasharray": null
              }
            },
            "width": 200,
            "height": 100,
            "zIndex": 10,
            "connector": "smooth",
            "data": {
              "type": "tm.Flow",
              "name": "Data Flow",
              "description": "",
              "outOfScope": false,
              "isTrustBoundary": false,
              "reasonOutOfScope": "",
              "hasOpenThreats": false,
              "isBidirectional": false,
              "isEncrypted": false,
              "isPublicNetwork": false,
              "protocol": "",
              "threats": [],
              "trustBoundaryIds": []
            },
            "labels": [
              "Data Flow"
            ],
            "id": "f091a9b5-f72a-4360-bd08-15940b0a5fa9",
            "source": {
              "x": 565,
              "y": 240
            },
            "target": {
              "cell": "231ffb1b-09a5-4a90-bed6-dfaacc8885b4",
              "port": "1c6ee9a6-8911-4d7b-80cc-c69e404bab7d"
            }
          },
          {
            "shape": "flow",
            "attrs": {
              "line": {
                "stroke": "#333333",
                "targetMarker": {
                  "name": "block"
                },
                "sourceMarker": {
                  "name": ""
                },
                "strokeDasharray": null
              }
            },
            "width": 200,
            "height": 100,
            "zIndex": 10,
            "connector": "smooth",
            "data": {
              "type": "tm.Flow",
              "name": "Data Flow",
              "description": "",
              "outOfScope": false,
              "isTrustBoundary": false,
              "reasonOutOfScope": "",
              "hasOpenThreats": false,
              "isBidirectional": false,
              "isEncrypted": false,
              "isPublicNetwork": false,
              "protocol": "",
              "threats": [],
              "trustBoundaryIds": []
            },
            "labels": [
              "Data Flow"
            ],
            "id": "c0f40f0d-ac01-4804-a7db-3ec606cc7c0d",
            "source": {
              "x": 560,
              "y": 60
            },
            "target": {
              "cell": "fbdaa8c5-67ed-4f80-a24c-fd678d66eb6e",
              "port": "1c6ee9a6-8911-4d7b-80cc-c69e404bab7d"
            }
          },
          {
            "position": {
              "x": 704,
              "y": 35
            },
            "size": {
              "width": 120,
              "height": 60
            },
            "attrs": {
              "text": {
                "text": "Database Akun"
              },
              "topLine": {
                "stroke": "red",
                "strokeWidth": 2.5,
                "strokeDasharray": null
              },
              "bottomLine": {
                "stroke": "red",
                "strokeWidth": 2.5,
                "strokeDasharray": null
              }
            },
            "visible": true,
            "shape": "store",
            "zIndex": 11,
            "ports": {
              "groups": {
                "top": {
                  "position": "top",
                  "attrs": {
                    "circle": {
                      "r": 4,
                      "magnet": true,
                      "stroke": "#5F95FF",
                      "strokeWidth": 1,
                      "fill": "#fff",
                      "style": {
                        "visibility": "hidden"
                      }
                    }
                  }
                },
                "right": {
                  "position": "right",
                  "attrs": {
                    "circle": {
                      "r": 4,
                      "magnet": true,
                      "stroke": "#5F95FF",
                      "strokeWidth": 1,
                      "fill": "#fff",
                      "style": {
                        "visibility": "hidden"
                      }
                    }
                  }
                },
                "bottom": {
                  "position": "bottom",
                  "attrs": {
                    "circle": {
                      "r": 4,
                      "magnet": true,
                      "stroke": "#5F95FF",
                      "strokeWidth": 1,
                      "fill": "#fff",
                      "style": {
                        "visibility": "hidden"
                      }
                    }
                  }
                },
                "left": {
                  "position": "left",
                  "attrs": {
                    "circle": {
                      "r": 4,
                      "magnet": true,
                      "stroke": "#5F95FF",
                      "strokeWidth": 1,
                      "fill": "#fff",
                      "style": {
                        "visibility": "hidden"
                      }
                    }
                  }
                }
              },
              "items": [
                {
                  "group": "top",
                  "id": "b7bcdc3e-2bc7-4f12-b6c1-03ceaa7243bb"
                },
                {
                  "group": "right",
                  "id": "46427411-4a58-4abe-a1c5-6bfbaa462b58"
                },
                {
                  "group": "bottom",
                  "id": "b966d9dd-111f-4561-b336-223e83254ea0"
                },
                {
                  "group": "left",
                  "id": "1c6ee9a6-8911-4d7b-80cc-c69e404bab7d"
                }
              ]
            },
            "id": "fbdaa8c5-67ed-4f80-a24c-fd678d66eb6e",
            "data": {
              "type": "tm.Store",
              "name": "Database Akun",
              "description": "",
              "outOfScope": false,
              "isTrustBoundary": false,
              "reasonOutOfScope": "",
              "hasOpenThreats": true,
              "isALog": false,
              "isEncrypted": false,
              "isSigned": false,
              "storesCredentials": false,
              "storesInventory": false,
              "threats": [
                {
                  "id": "828dc123-8260-45bd-8e9f-de6ba7c987a0",
                  "title": "Data dimodifikasi",
                  "status": "Open",
                  "severity": "High",
                  "type": "Tampering",
                  "description": "Data akun dimodifikasi secara langsung tanpa otentikasi",
                  "mitigation": "DB ACL, Audit DB",
                  "modelType": "STRIDE",
                  "new": false,
                  "number": 12,
                  "score": "16"
                },
                {
                  "id": "ae32a19e-9f67-4e02-b9dd-bf642f9a8248",
                  "title": "Data akun bocor",
                  "status": "Open",
                  "severity": "High",
                  "type": "Information disclosure",
                  "description": "Pelanggaran privasi",
                  "mitigation": "Enkripsi",
                  "modelType": "STRIDE",
                  "new": false,
                  "number": 13,
                  "score": "16"
                }
              ],
              "threatFrequency": {
                "tampering": 1,
                "repudiation": 0,
                "informationDisclosure": 1,
                "denialOfService": 0
              }
            }
          },
          {
            "position": {
              "x": 704,
              "y": 210
            },
            "size": {
              "width": 120,
              "height": 60
            },
            "attrs": {
              "text": {
                "text": "Database Audit\n& Auth Log"
              },
              "topLine": {
                "stroke": "red",
                "strokeWidth": 2.5,
                "strokeDasharray": null
              },
              "bottomLine": {
                "stroke": "red",
                "strokeWidth": 2.5,
                "strokeDasharray": null
              }
            },
            "visible": true,
            "shape": "store",
            "zIndex": 12,
            "ports": {
              "groups": {
                "top": {
                  "position": "top",
                  "attrs": {
                    "circle": {
                      "r": 4,
                      "magnet": true,
                      "stroke": "#5F95FF",
                      "strokeWidth": 1,
                      "fill": "#fff",
                      "style": {
                        "visibility": "hidden"
                      }
                    }
                  }
                },
                "right": {
                  "position": "right",
                  "attrs": {
                    "circle": {
                      "r": 4,
                      "magnet": true,
                      "stroke": "#5F95FF",
                      "strokeWidth": 1,
                      "fill": "#fff",
                      "style": {
                        "visibility": "hidden"
                      }
                    }
                  }
                },
                "bottom": {
                  "position": "bottom",
                  "attrs": {
                    "circle": {
                      "r": 4,
                      "magnet": true,
                      "stroke": "#5F95FF",
                      "strokeWidth": 1,
                      "fill": "#fff",
                      "style": {
                        "visibility": "hidden"
                      }
                    }
                  }
                },
                "left": {
                  "position": "left",
                  "attrs": {
                    "circle": {
                      "r": 4,
                      "magnet": true,
                      "stroke": "#5F95FF",
                      "strokeWidth": 1,
                      "fill": "#fff",
                      "style": {
                        "visibility": "hidden"
                      }
                    }
                  }
                }
              },
              "items": [
                {
                  "group": "top",
                  "id": "b7bcdc3e-2bc7-4f12-b6c1-03ceaa7243bb"
                },
                {
                  "group": "right",
                  "id": "46427411-4a58-4abe-a1c5-6bfbaa462b58"
                },
                {
                  "group": "bottom",
                  "id": "b966d9dd-111f-4561-b336-223e83254ea0"
                },
                {
                  "group": "left",
                  "id": "1c6ee9a6-8911-4d7b-80cc-c69e404bab7d"
                }
              ]
            },
            "id": "231ffb1b-09a5-4a90-bed6-dfaacc8885b4",
            "data": {
              "type": "tm.Store",
              "name": "Database Audit\n& Auth Log",
              "description": "",
              "outOfScope": false,
              "isTrustBoundary": false,
              "reasonOutOfScope": "",
              "hasOpenThreats": true,
              "isALog": false,
              "isEncrypted": false,
              "isSigned": false,
              "storesCredentials": false,
              "storesInventory": false,
              "threats": [
                {
                  "id": "25871c72-fe03-4cf4-97e2-aed159579278",
                  "title": "Perubahan Log",
                  "status": "Open",
                  "severity": "High",
                  "type": "Tampering",
                  "description": "Hilang jejak Forensik",
                  "mitigation": "Immutable/append-only",
                  "modelType": "STRIDE",
                  "new": false,
                  "number": 16,
                  "score": "16"
                },
                {
                  "id": "8ad943d8-3dd4-4d0e-aafa-38cc5cb4028a",
                  "title": "Penyangkalan Aktivitas",
                  "status": "Open",
                  "severity": "Medium",
                  "type": "Repudiation",
                  "description": "Bukti tidak kuat",
                  "mitigation": "Signed Log, Timestamp, Blockchain",
                  "modelType": "STRIDE",
                  "new": false,
                  "number": 17,
                  "score": "9"
                },
                {
                  "id": "f3b352b2-e726-4956-8599-82b3a55819b1",
                  "title": "Audit Log Bocot",
                  "status": "Open",
                  "severity": "High",
                  "type": "Information disclosure",
                  "description": "informasi internal terbuka",
                  "mitigation": "kontrol akses, enkripsi",
                  "modelType": "STRIDE",
                  "new": false,
                  "number": 18,
                  "score": "16"
                }
              ],
              "threatFrequency": {
                "tampering": 1,
                "repudiation": 1,
                "informationDisclosure": 1,
                "denialOfService": 0
              }
            },
            "tools": {
              "items": [
                "boundary",
                "button-remove"
              ],
              "name": null
            }
          }
        ]
      },
      {
        "id": 1,
        "title": "User (Registration, Nurse, Doctor)",
        "diagramType": "STRIDE",
        "placeholder": "New STRIDE diagram description",
        "thumbnail": "./public/content/images/thumbnail.stride.jpg",
        "version": "2.5.0",
        "cells": [
          {
            "position": {
              "x": 150,
              "y": 110
            },
            "size": {
              "width": 112.5,
              "height": 60
            },
            "attrs": {
              "text": {
                "text": "Pendaftaran"
              },
              "body": {
                "stroke": "red",
                "strokeWidth": 2.5,
                "strokeDasharray": null
              }
            },
            "visible": true,
            "shape": "actor",
            "zIndex": 1,
            "ports": {
              "groups": {
                "top": {
                  "position": "top",
                  "attrs": {
                    "circle": {
                      "r": 4,
                      "magnet": true,
                      "stroke": "#5F95FF",
                      "strokeWidth": 1,
                      "fill": "#fff",
                      "style": {
                        "visibility": "hidden"
                      }
                    }
                  }
                },
                "right": {
                  "position": "right",
                  "attrs": {
                    "circle": {
                      "r": 4,
                      "magnet": true,
                      "stroke": "#5F95FF",
                      "strokeWidth": 1,
                      "fill": "#fff",
                      "style": {
                        "visibility": "hidden"
                      }
                    }
                  }
                },
                "bottom": {
                  "position": "bottom",
                  "attrs": {
                    "circle": {
                      "r": 4,
                      "magnet": true,
                      "stroke": "#5F95FF",
                      "strokeWidth": 1,
                      "fill": "#fff",
                      "style": {
                        "visibility": "hidden"
                      }
                    }
                  }
                },
                "left": {
                  "position": "left",
                  "attrs": {
                    "circle": {
                      "r": 4,
                      "magnet": true,
                      "stroke": "#5F95FF",
                      "strokeWidth": 1,
                      "fill": "#fff",
                      "style": {
                        "visibility": "hidden"
                      }
                    }
                  }
                }
              },
              "items": [
                {
                  "group": "top",
                  "id": "98ab7ada-d2e8-4211-b951-dd282baaaec8"
                },
                {
                  "group": "right",
                  "id": "3efd3554-e3b0-460a-93bd-34c139e7749e"
                },
                {
                  "group": "bottom",
                  "id": "65a270f2-d934-4078-98be-37952422afa1"
                },
                {
                  "group": "left",
                  "id": "83e5645c-afe5-440c-800f-293cec4d911d"
                }
              ]
            },
            "id": "8ca6ae63-efe5-49db-ab06-8f19b9ff0624",
            "data": {
              "type": "tm.Actor",
              "name": "Pendaftaran",
              "description": "",
              "isTrustBoundary": false,
              "outOfScope": false,
              "reasonOutOfScope": "",
              "hasOpenThreats": true,
              "providesAuthentication": false,
              "threats": [
                {
                  "id": "4748e88c-f85b-4ba1-8f4b-1119e8ba5b02",
                  "title": "User palsu menyamar pendaftaran",
                  "status": "Mitigated",
                  "severity": "High",
                  "type": "Spoofing",
                  "description": "Data pasien fiktif",
                  "mitigation": "Penggunaan sistem secara lokal, memperkuat akses lokal",
                  "modelType": "STRIDE",
                  "new": false,
                  "number": 22,
                  "score": "16"
                },
                {
                  "id": "61eb38d6-8f71-4e0d-ac37-d6f2fe85eb8f",
                  "title": "Penyangkalan input data pasien",
                  "status": "Open",
                  "severity": "Medium",
                  "type": "Repudiation",
                  "description": "Sengketa data",
                  "mitigation": "Audit Log",
                  "modelType": "STRIDE",
                  "new": false,
                  "number": 23,
                  "score": "9"
                }
              ],
              "threatFrequency": {
                "spoofing": 1,
                "repudiation": 1
              }
            }
          },
          {
            "position": {
              "x": 150,
              "y": 462
            },
            "size": {
              "width": 112.5,
              "height": 60
            },
            "attrs": {
              "text": {
                "text": "Doctor"
              },
              "body": {
                "stroke": "red",
                "strokeWidth": 2.5,
                "strokeDasharray": null
              }
            },
            "visible": true,
            "shape": "actor",
            "zIndex": 3,
            "ports": {
              "groups": {
                "top": {
                  "position": "top",
                  "attrs": {
                    "circle": {
                      "r": 4,
                      "magnet": true,
                      "stroke": "#5F95FF",
                      "strokeWidth": 1,
                      "fill": "#fff",
                      "style": {
                        "visibility": "hidden"
                      }
                    }
                  }
                },
                "right": {
                  "position": "right",
                  "attrs": {
                    "circle": {
                      "r": 4,
                      "magnet": true,
                      "stroke": "#5F95FF",
                      "strokeWidth": 1,
                      "fill": "#fff",
                      "style": {
                        "visibility": "hidden"
                      }
                    }
                  }
                },
                "bottom": {
                  "position": "bottom",
                  "attrs": {
                    "circle": {
                      "r": 4,
                      "magnet": true,
                      "stroke": "#5F95FF",
                      "strokeWidth": 1,
                      "fill": "#fff",
                      "style": {
                        "visibility": "hidden"
                      }
                    }
                  }
                },
                "left": {
                  "position": "left",
                  "attrs": {
                    "circle": {
                      "r": 4,
                      "magnet": true,
                      "stroke": "#5F95FF",
                      "strokeWidth": 1,
                      "fill": "#fff",
                      "style": {
                        "visibility": "hidden"
                      }
                    }
                  }
                }
              },
              "items": [
                {
                  "group": "top",
                  "id": "98ab7ada-d2e8-4211-b951-dd282baaaec8"
                },
                {
                  "group": "right",
                  "id": "3efd3554-e3b0-460a-93bd-34c139e7749e"
                },
                {
                  "group": "bottom",
                  "id": "65a270f2-d934-4078-98be-37952422afa1"
                },
                {
                  "group": "left",
                  "id": "83e5645c-afe5-440c-800f-293cec4d911d"
                }
              ]
            },
            "id": "2d8106f5-eb57-4c4d-ba7e-65bd1013eb9f",
            "data": {
              "type": "tm.Actor",
              "name": "Doctor",
              "description": "",
              "isTrustBoundary": false,
              "outOfScope": false,
              "reasonOutOfScope": "",
              "hasOpenThreats": true,
              "providesAuthentication": false,
              "threats": [
                {
                  "id": "d18175ed-4007-49be-bc91-0c82cdc65d37",
                  "title": "Akun dokter dicuri",
                  "status": "Mitigated",
                  "severity": "Critical",
                  "type": "Spoofing",
                  "description": "Diagnosa & Terapi salah",
                  "mitigation": "pengawasan dan penggunaan jaringan lokal yang ketat",
                  "modelType": "STRIDE",
                  "new": false,
                  "number": 34,
                  "score": "20"
                },
                {
                  "id": "7038f799-2337-4b45-8ca8-7addc7158a77",
                  "title": "Dokter menyangkal tindakan yang telah diambil",
                  "status": "Open",
                  "severity": "Medium",
                  "type": "Repudiation",
                  "description": "Masalah Hukum ",
                  "mitigation": "Audit Log yang terhubung dengan blockchain",
                  "modelType": "STRIDE",
                  "new": false,
                  "number": 35,
                  "score": "12"
                }
              ],
              "threatFrequency": {
                "spoofing": 1,
                "repudiation": 1
              }
            }
          },
          {
            "position": {
              "x": 441,
              "y": 90
            },
            "size": {
              "width": 110,
              "height": 100
            },
            "attrs": {
              "text": {
                "text": "Membuat \nRekam Medis"
              },
              "body": {
                "stroke": "red",
                "strokeWidth": 2.5,
                "strokeDasharray": null
              }
            },
            "visible": true,
            "shape": "process",
            "zIndex": 4,
            "ports": {
              "groups": {
                "top": {
                  "position": "top",
                  "attrs": {
                    "circle": {
                      "r": 4,
                      "magnet": true,
                      "stroke": "#5F95FF",
                      "strokeWidth": 1,
                      "fill": "#fff",
                      "style": {
                        "visibility": "hidden"
                      }
                    }
                  }
                },
                "right": {
                  "position": "right",
                  "attrs": {
                    "circle": {
                      "r": 4,
                      "magnet": true,
                      "stroke": "#5F95FF",
                      "strokeWidth": 1,
                      "fill": "#fff",
                      "style": {
                        "visibility": "hidden"
                      }
                    }
                  }
                },
                "bottom": {
                  "position": "bottom",
                  "attrs": {
                    "circle": {
                      "r": 4,
                      "magnet": true,
                      "stroke": "#5F95FF",
                      "strokeWidth": 1,
                      "fill": "#fff",
                      "style": {
                        "visibility": "hidden"
                      }
                    }
                  }
                },
                "left": {
                  "position": "left",
                  "attrs": {
                    "circle": {
                      "r": 4,
                      "magnet": true,
                      "stroke": "#5F95FF",
                      "strokeWidth": 1,
                      "fill": "#fff",
                      "style": {
                        "visibility": "hidden"
                      }
                    }
                  }
                }
              },
              "items": [
                {
                  "group": "top",
                  "id": "d68cbf7c-b32d-4305-be14-26af60ec0e27"
                },
                {
                  "group": "right",
                  "id": "1c51061f-6cc4-40f3-907b-d922a5a83e51"
                },
                {
                  "group": "bottom",
                  "id": "ea09d88d-10f6-48e2-81b3-9b80d620f224"
                },
                {
                  "group": "left",
                  "id": "72b88cbd-5622-4b04-8e90-58805bd74d49"
                }
              ]
            },
            "id": "de76b33d-2691-450a-8b03-0b198ba9c682",
            "data": {
              "type": "tm.Process",
              "name": "Membuat \nRekam Medis",
              "description": "",
              "outOfScope": false,
              "isTrustBoundary": false,
              "reasonOutOfScope": "",
              "hasOpenThreats": true,
              "handlesCardPayment": false,
              "handlesGoodsOrServices": false,
              "isWebApplication": false,
              "privilegeLevel": "",
              "threats": [
                {
                  "id": "cbb5f8d9-053d-487b-b00a-29fbb9fb1e21",
                  "title": "Data pasien dimodifikasi",
                  "status": "Open",
                  "severity": "High",
                  "type": "Tampering",
                  "description": "Data medis salah",
                  "mitigation": "Validation, checksum",
                  "modelType": "STRIDE",
                  "new": false,
                  "number": 25,
                  "score": "16"
                },
                {
                  "id": "c4e3ac47-b43b-4843-9f8a-9f6c813b71a8",
                  "title": "Tidak ada jejak pembuatan RM",
                  "status": "Open",
                  "severity": "Medium",
                  "type": "Repudiation",
                  "description": "Audit gagal",
                  "mitigation": "Timestamp + user ID",
                  "modelType": "STRIDE",
                  "new": false,
                  "number": 26,
                  "score": "9"
                },
                {
                  "id": "3c9cbd00-a3b1-416d-88af-5012cb552801",
                  "title": "Data sensitif terekspos",
                  "status": "Open",
                  "severity": "Critical",
                  "type": "Information disclosure",
                  "description": "Pelanggaran privasi",
                  "mitigation": "Encryption, penggunaan secara lokal",
                  "modelType": "STRIDE",
                  "new": false,
                  "number": 27,
                  "score": "20"
                }
              ],
              "threatFrequency": {
                "spoofing": 0,
                "tampering": 1,
                "repudiation": 1,
                "informationDisclosure": 1,
                "denialOfService": 0,
                "elevationOfPrivilege": 0
              }
            }
          },
          {
            "position": {
              "x": 441,
              "y": 281
            },
            "size": {
              "width": 110,
              "height": 100
            },
            "attrs": {
              "text": {
                "text": "Membuat \nDiagnosis \nawal pasien"
              },
              "body": {
                "stroke": "#333333",
                "strokeWidth": 1.5,
                "strokeDasharray": null
              }
            },
            "visible": true,
            "shape": "process",
            "zIndex": 5,
            "ports": {
              "groups": {
                "top": {
                  "position": "top",
                  "attrs": {
                    "circle": {
                      "r": 4,
                      "magnet": true,
                      "stroke": "#5F95FF",
                      "strokeWidth": 1,
                      "fill": "#fff",
                      "style": {
                        "visibility": "hidden"
                      }
                    }
                  }
                },
                "right": {
                  "position": "right",
                  "attrs": {
                    "circle": {
                      "r": 4,
                      "magnet": true,
                      "stroke": "#5F95FF",
                      "strokeWidth": 1,
                      "fill": "#fff",
                      "style": {
                        "visibility": "hidden"
                      }
                    }
                  }
                },
                "bottom": {
                  "position": "bottom",
                  "attrs": {
                    "circle": {
                      "r": 4,
                      "magnet": true,
                      "stroke": "#5F95FF",
                      "strokeWidth": 1,
                      "fill": "#fff",
                      "style": {
                        "visibility": "hidden"
                      }
                    }
                  }
                },
                "left": {
                  "position": "left",
                  "attrs": {
                    "circle": {
                      "r": 4,
                      "magnet": true,
                      "stroke": "#5F95FF",
                      "strokeWidth": 1,
                      "fill": "#fff",
                      "style": {
                        "visibility": "hidden"
                      }
                    }
                  }
                }
              },
              "items": [
                {
                  "group": "top",
                  "id": "d68cbf7c-b32d-4305-be14-26af60ec0e27"
                },
                {
                  "group": "right",
                  "id": "1c51061f-6cc4-40f3-907b-d922a5a83e51"
                },
                {
                  "group": "bottom",
                  "id": "ea09d88d-10f6-48e2-81b3-9b80d620f224"
                },
                {
                  "group": "left",
                  "id": "72b88cbd-5622-4b04-8e90-58805bd74d49"
                }
              ]
            },
            "id": "7ca3781d-9f14-4de9-8824-e0d21da71964",
            "data": {
              "type": "tm.Process",
              "name": "Membuat \nDiagnosis \nawal pasien",
              "description": "",
              "outOfScope": false,
              "isTrustBoundary": false,
              "reasonOutOfScope": "",
              "hasOpenThreats": false,
              "handlesCardPayment": false,
              "handlesGoodsOrServices": false,
              "isWebApplication": false,
              "privilegeLevel": "",
              "threats": [
                {
                  "id": "e47040da-5300-4c42-81ee-3e739bb0bc74",
                  "title": "Data keluhan diubah",
                  "status": "Mitigated",
                  "severity": "High",
                  "type": "Tampering",
                  "description": "Diagnosis keliru",
                  "mitigation": "Validation",
                  "modelType": "STRIDE",
                  "new": false,
                  "number": 31,
                  "score": "16"
                },
                {
                  "id": "b4684137-969e-4ea6-aaed-c685305e5ad6",
                  "title": "Riwayat Pasien Bocor",
                  "status": "Mitigated",
                  "severity": "Critical",
                  "type": "Information disclosure",
                  "description": "Pelanggaran privasi",
                  "mitigation": "Field Masking, Sensor NIK",
                  "modelType": "STRIDE",
                  "new": false,
                  "number": 32,
                  "score": "20"
                },
                {
                  "id": "655b8df8-626f-4c10-817d-27f1c07e9026",
                  "title": "Input berulang kali ",
                  "status": "Mitigated",
                  "severity": "Medium",
                  "type": "Denial of service",
                  "description": "Delay layanan",
                  "mitigation": "Throttling",
                  "modelType": "STRIDE",
                  "new": false,
                  "number": 33,
                  "score": "9"
                }
              ],
              "threatFrequency": {
                "spoofing": 0,
                "tampering": 1,
                "repudiation": 0,
                "informationDisclosure": 1,
                "denialOfService": 1,
                "elevationOfPrivilege": 0
              }
            }
          },
          {
            "position": {
              "x": 441,
              "y": 442
            },
            "size": {
              "width": 110,
              "height": 100
            },
            "attrs": {
              "text": {
                "text": "Melakukan\nPemeriksaan\nPasien"
              },
              "body": {
                "stroke": "red",
                "strokeWidth": 2.5,
                "strokeDasharray": null
              }
            },
            "visible": true,
            "shape": "process",
            "zIndex": 6,
            "ports": {
              "groups": {
                "top": {
                  "position": "top",
                  "attrs": {
                    "circle": {
                      "r": 4,
                      "magnet": true,
                      "stroke": "#5F95FF",
                      "strokeWidth": 1,
                      "fill": "#fff",
                      "style": {
                        "visibility": "hidden"
                      }
                    }
                  }
                },
                "right": {
                  "position": "right",
                  "attrs": {
                    "circle": {
                      "r": 4,
                      "magnet": true,
                      "stroke": "#5F95FF",
                      "strokeWidth": 1,
                      "fill": "#fff",
                      "style": {
                        "visibility": "hidden"
                      }
                    }
                  }
                },
                "bottom": {
                  "position": "bottom",
                  "attrs": {
                    "circle": {
                      "r": 4,
                      "magnet": true,
                      "stroke": "#5F95FF",
                      "strokeWidth": 1,
                      "fill": "#fff",
                      "style": {
                        "visibility": "hidden"
                      }
                    }
                  }
                },
                "left": {
                  "position": "left",
                  "attrs": {
                    "circle": {
                      "r": 4,
                      "magnet": true,
                      "stroke": "#5F95FF",
                      "strokeWidth": 1,
                      "fill": "#fff",
                      "style": {
                        "visibility": "hidden"
                      }
                    }
                  }
                }
              },
              "items": [
                {
                  "group": "top",
                  "id": "d68cbf7c-b32d-4305-be14-26af60ec0e27"
                },
                {
                  "group": "right",
                  "id": "1c51061f-6cc4-40f3-907b-d922a5a83e51"
                },
                {
                  "group": "bottom",
                  "id": "ea09d88d-10f6-48e2-81b3-9b80d620f224"
                },
                {
                  "group": "left",
                  "id": "72b88cbd-5622-4b04-8e90-58805bd74d49"
                }
              ]
            },
            "id": "d085f64e-a85f-4a89-9637-ffdf43fe005d",
            "data": {
              "type": "tm.Process",
              "name": "Melakukan\nPemeriksaan\nPasien",
              "description": "",
              "outOfScope": false,
              "isTrustBoundary": false,
              "reasonOutOfScope": "",
              "hasOpenThreats": true,
              "handlesCardPayment": false,
              "handlesGoodsOrServices": false,
              "isWebApplication": false,
              "privilegeLevel": "",
              "threats": [
                {
                  "id": "15b149b1-b303-4bdb-9006-670df9649c7c",
                  "title": "Hasil Pemeriksaan diubah",
                  "status": "Open",
                  "severity": "Critical",
                  "type": "Tampering",
                  "description": "Data pasien yang sudah final dapat diubah-ubah sehingga salah pengobatan",
                  "mitigation": "Integrity Check, Finalisasi saat sudah SEND oleh dokter (tidak bisa diubah)",
                  "modelType": "STRIDE",
                  "new": false,
                  "number": 36,
                  "score": "20"
                },
                {
                  "id": "7aafd351-8ee1-4999-bd4e-8a5dc61b5df0",
                  "title": "Tiada jejak Finalisasi",
                  "status": "Open",
                  "severity": "Medium",
                  "type": "Repudiation",
                  "description": "Audit gagal",
                  "mitigation": "Status Final + Audit Log yang terhubung dengan blockchain",
                  "modelType": "STRIDE",
                  "new": false,
                  "number": 37,
                  "score": "12"
                },
                {
                  "id": "84aace82-ab7f-42d9-852f-e7abfddf2c60",
                  "title": "SOAP Bocor",
                  "status": "Open",
                  "severity": "TBD",
                  "type": "Information disclosure",
                  "description": "Pelanggaran Privasi",
                  "mitigation": "Enkripsi dan pengamanan jaringan lokal",
                  "modelType": "STRIDE",
                  "new": false,
                  "number": 38,
                  "score": "20"
                }
              ],
              "threatFrequency": {
                "spoofing": 0,
                "tampering": 1,
                "repudiation": 1,
                "informationDisclosure": 1,
                "denialOfService": 0,
                "elevationOfPrivilege": 0
              }
            }
          },
          {
            "position": {
              "x": 733,
              "y": 301
            },
            "size": {
              "width": 120,
              "height": 60
            },
            "attrs": {
              "text": {
                "text": "Database Pasien"
              },
              "topLine": {
                "stroke": "red",
                "strokeWidth": 2.5,
                "strokeDasharray": null
              },
              "bottomLine": {
                "stroke": "red",
                "strokeWidth": 2.5,
                "strokeDasharray": null
              }
            },
            "visible": true,
            "shape": "store",
            "zIndex": 7,
            "ports": {
              "groups": {
                "top": {
                  "position": "top",
                  "attrs": {
                    "circle": {
                      "r": 4,
                      "magnet": true,
                      "stroke": "#5F95FF",
                      "strokeWidth": 1,
                      "fill": "#fff",
                      "style": {
                        "visibility": "hidden"
                      }
                    }
                  }
                },
                "right": {
                  "position": "right",
                  "attrs": {
                    "circle": {
                      "r": 4,
                      "magnet": true,
                      "stroke": "#5F95FF",
                      "strokeWidth": 1,
                      "fill": "#fff",
                      "style": {
                        "visibility": "hidden"
                      }
                    }
                  }
                },
                "bottom": {
                  "position": "bottom",
                  "attrs": {
                    "circle": {
                      "r": 4,
                      "magnet": true,
                      "stroke": "#5F95FF",
                      "strokeWidth": 1,
                      "fill": "#fff",
                      "style": {
                        "visibility": "hidden"
                      }
                    }
                  }
                },
                "left": {
                  "position": "left",
                  "attrs": {
                    "circle": {
                      "r": 4,
                      "magnet": true,
                      "stroke": "#5F95FF",
                      "strokeWidth": 1,
                      "fill": "#fff",
                      "style": {
                        "visibility": "hidden"
                      }
                    }
                  }
                }
              },
              "items": [
                {
                  "group": "top",
                  "id": "dfb4c0f2-fa6f-4674-af5e-61041b21500a"
                },
                {
                  "group": "right",
                  "id": "e1381148-1ca4-4edd-9894-a9ee12ba06f7"
                },
                {
                  "group": "bottom",
                  "id": "c10dc629-145d-45b1-93dc-e882c82dc251"
                },
                {
                  "group": "left",
                  "id": "18c7217f-4dc4-448e-b21f-42ef138af8a4"
                }
              ]
            },
            "id": "b94426d1-d9ad-4b7d-b3ba-f89b9911e2f7",
            "data": {
              "type": "tm.Store",
              "name": "Database Pasien",
              "description": "",
              "outOfScope": false,
              "isTrustBoundary": false,
              "reasonOutOfScope": "",
              "hasOpenThreats": true,
              "isALog": false,
              "isEncrypted": false,
              "isSigned": false,
              "storesCredentials": false,
              "storesInventory": false,
              "threats": [
                {
                  "id": "a78da79b-8ee8-49ab-ab5c-93f82dea7535",
                  "title": "Rekam medis diubah langsung",
                  "status": "Mitigated",
                  "severity": "High",
                  "type": "Tampering",
                  "description": "Kesalahan diagnosis",
                  "mitigation": "audit DB",
                  "modelType": "STRIDE",
                  "new": false,
                  "number": 28,
                  "score": "16"
                },
                {
                  "id": "cc53f8b9-c463-46e2-88d6-212503dd00bc",
                  "title": "Kebocoran data pasien",
                  "status": "Mitigated",
                  "severity": "Critical",
                  "type": "Information disclosure",
                  "description": "Legal & etika",
                  "mitigation": "Enkripsi",
                  "modelType": "STRIDE",
                  "new": false,
                  "number": 29,
                  "score": "20"
                },
                {
                  "id": "c3375501-3ab4-4414-998a-e3f8692ed903",
                  "title": "DB Overload Input",
                  "status": "Open",
                  "severity": "Medium",
                  "type": "Denial of service",
                  "description": "Sistem Down",
                  "mitigation": "Rate limit",
                  "modelType": "STRIDE",
                  "new": false,
                  "number": 30,
                  "score": "12"
                }
              ],
              "threatFrequency": {
                "tampering": 1,
                "repudiation": 0,
                "informationDisclosure": 1,
                "denialOfService": 1
              }
            }
          },
          {
            "shape": "flow",
            "attrs": {
              "line": {
                "stroke": "#333333",
                "targetMarker": {
                  "name": "block"
                },
                "sourceMarker": {
                  "name": ""
                },
                "strokeDasharray": null
              }
            },
            "width": 200,
            "height": 100,
            "zIndex": 10,
            "connector": "smooth",
            "data": {
              "type": "tm.Flow",
              "name": "Data Flow",
              "description": "",
              "outOfScope": false,
              "isTrustBoundary": false,
              "reasonOutOfScope": "",
              "hasOpenThreats": false,
              "isBidirectional": false,
              "isEncrypted": false,
              "isPublicNetwork": false,
              "protocol": "",
              "threats": [],
              "trustBoundaryIds": []
            },
            "labels": [
              "Data Flow"
            ],
            "id": "bbb23bfa-46ce-4302-90c1-80ccabb29792",
            "source": {
              "x": 263,
              "y": 130
            },
            "target": {
              "cell": "de76b33d-2691-450a-8b03-0b198ba9c682",
              "port": "72b88cbd-5622-4b04-8e90-58805bd74d49"
            },
            "vertices": [
              {
                "x": 350,
                "y": 130
              }
            ]
          },
          {
            "shape": "flow",
            "attrs": {
              "line": {
                "stroke": "#333333",
                "targetMarker": {
                  "name": "block"
                },
                "sourceMarker": {
                  "name": ""
                },
                "strokeDasharray": null
              }
            },
            "width": 200,
            "height": 100,
            "zIndex": 10,
            "connector": "smooth",
            "data": {
              "type": "tm.Flow",
              "name": "Data Flow",
              "description": "",
              "outOfScope": false,
              "isTrustBoundary": false,
              "reasonOutOfScope": "",
              "hasOpenThreats": false,
              "isBidirectional": false,
              "isEncrypted": false,
              "isPublicNetwork": false,
              "protocol": "",
              "threats": [],
              "trustBoundaryIds": []
            },
            "labels": [
              "Data Flow"
            ],
            "id": "405fde73-aaad-4a54-9991-3fa4e3ffa4bb",
            "source": {
              "x": 551,
              "y": 140
            },
            "target": {
              "cell": "b94426d1-d9ad-4b7d-b3ba-f89b9911e2f7",
              "port": "dfb4c0f2-fa6f-4674-af5e-61041b21500a"
            }
          },
          {
            "shape": "flow",
            "attrs": {
              "line": {
                "stroke": "#333333",
                "targetMarker": {
                  "name": "block"
                },
                "sourceMarker": {
                  "name": ""
                },
                "strokeDasharray": null
              }
            },
            "width": 200,
            "height": 100,
            "zIndex": 10,
            "connector": "smooth",
            "data": {
              "type": "tm.Flow",
              "name": "Data Flow",
              "description": "",
              "outOfScope": false,
              "isTrustBoundary": false,
              "reasonOutOfScope": "",
              "hasOpenThreats": false,
              "isBidirectional": false,
              "isEncrypted": false,
              "isPublicNetwork": false,
              "protocol": "",
              "threats": [],
              "trustBoundaryIds": []
            },
            "labels": [
              "Data Flow"
            ],
            "id": "0119e400-b5b1-4d9e-b0ee-6905e20e4dad",
            "source": {
              "x": 263,
              "y": 321
            },
            "target": {
              "cell": "7ca3781d-9f14-4de9-8824-e0d21da71964",
              "port": "72b88cbd-5622-4b04-8e90-58805bd74d49"
            },
            "vertices": [
              {
                "x": 363,
                "y": 321
              }
            ]
          },
          {
            "shape": "flow",
            "attrs": {
              "line": {
                "stroke": "#333333",
                "targetMarker": {
                  "name": "block"
                },
                "sourceMarker": {
                  "name": ""
                },
                "strokeDasharray": null
              }
            },
            "width": 200,
            "height": 100,
            "zIndex": 10,
            "connector": "smooth",
            "data": {
              "type": "tm.Flow",
              "name": "Data Flow",
              "description": "",
              "outOfScope": false,
              "isTrustBoundary": false,
              "reasonOutOfScope": "",
              "hasOpenThreats": false,
              "isBidirectional": false,
              "isEncrypted": false,
              "isPublicNetwork": false,
              "protocol": "",
              "threats": [],
              "trustBoundaryIds": []
            },
            "labels": [
              "Data Flow"
            ],
            "id": "81284006-9425-4d13-9e6e-531b68d8c5c6",
            "source": {
              "x": 551,
              "y": 334
            },
            "target": {
              "cell": "b94426d1-d9ad-4b7d-b3ba-f89b9911e2f7",
              "port": "18c7217f-4dc4-448e-b21f-42ef138af8a4"
            },
            "vertices": [
              {
                "x": 650,
                "y": 334
              }
            ]
          },
          {
            "shape": "flow",
            "attrs": {
              "line": {
                "stroke": "#333333",
                "targetMarker": {
                  "name": "block"
                },
                "sourceMarker": {
                  "name": ""
                },
                "strokeDasharray": null
              }
            },
            "width": 200,
            "height": 100,
            "zIndex": 10,
            "connector": "smooth",
            "data": {
              "type": "tm.Flow",
              "name": "Data Flow",
              "description": "",
              "outOfScope": false,
              "isTrustBoundary": false,
              "reasonOutOfScope": "",
              "hasOpenThreats": false,
              "isBidirectional": false,
              "isEncrypted": false,
              "isPublicNetwork": false,
              "protocol": "",
              "threats": [],
              "trustBoundaryIds": []
            },
            "labels": [
              "Data Flow"
            ],
            "id": "025aa793-a4c3-49d5-a3d9-8f1f494c714d",
            "source": {
              "cell": "2d8106f5-eb57-4c4d-ba7e-65bd1013eb9f",
              "port": "3efd3554-e3b0-460a-93bd-34c139e7749e"
            },
            "target": {
              "cell": "d085f64e-a85f-4a89-9637-ffdf43fe005d",
              "port": "72b88cbd-5622-4b04-8e90-58805bd74d49"
            }
          },
          {
            "shape": "flow",
            "attrs": {
              "line": {
                "stroke": "#333333",
                "targetMarker": {
                  "name": "block"
                },
                "sourceMarker": {
                  "name": ""
                },
                "strokeDasharray": null
              }
            },
            "width": 200,
            "height": 100,
            "zIndex": 10,
            "connector": "smooth",
            "data": {
              "type": "tm.Flow",
              "name": "Data Flow",
              "description": "",
              "outOfScope": false,
              "isTrustBoundary": false,
              "reasonOutOfScope": "",
              "hasOpenThreats": false,
              "isBidirectional": false,
              "isEncrypted": false,
              "isPublicNetwork": false,
              "protocol": "",
              "threats": [],
              "trustBoundaryIds": []
            },
            "labels": [
              "Data Flow"
            ],
            "id": "64b49f64-3d22-49fd-9645-82268befdc5e",
            "source": {
              "x": 550,
              "y": 490
            },
            "target": {
              "cell": "b94426d1-d9ad-4b7d-b3ba-f89b9911e2f7",
              "port": "c10dc629-145d-45b1-93dc-e882c82dc251"
            },
            "vertices": [
              {
                "x": 660,
                "y": 490
              }
            ]
          },
          {
            "position": {
              "x": 150,
              "y": 291
            },
            "size": {
              "width": 112.5,
              "height": 60
            },
            "attrs": {
              "text": {
                "text": "Nurse"
              },
              "body": {
                "stroke": "red",
                "strokeWidth": 2.5,
                "strokeDasharray": null
              }
            },
            "visible": true,
            "shape": "actor",
            "ports": {
              "groups": {
                "top": {
                  "position": "top",
                  "attrs": {
                    "circle": {
                      "r": 4,
                      "magnet": true,
                      "stroke": "#5F95FF",
                      "strokeWidth": 1,
                      "fill": "#fff",
                      "style": {
                        "visibility": "hidden"
                      }
                    }
                  }
                },
                "right": {
                  "position": "right",
                  "attrs": {
                    "circle": {
                      "r": 4,
                      "magnet": true,
                      "stroke": "#5F95FF",
                      "strokeWidth": 1,
                      "fill": "#fff",
                      "style": {
                        "visibility": "hidden"
                      }
                    }
                  }
                },
                "bottom": {
                  "position": "bottom",
                  "attrs": {
                    "circle": {
                      "r": 4,
                      "magnet": true,
                      "stroke": "#5F95FF",
                      "strokeWidth": 1,
                      "fill": "#fff",
                      "style": {
                        "visibility": "hidden"
                      }
                    }
                  }
                },
                "left": {
                  "position": "left",
                  "attrs": {
                    "circle": {
                      "r": 4,
                      "magnet": true,
                      "stroke": "#5F95FF",
                      "strokeWidth": 1,
                      "fill": "#fff",
                      "style": {
                        "visibility": "hidden"
                      }
                    }
                  }
                }
              },
              "items": [
                {
                  "group": "top",
                  "id": "98ab7ada-d2e8-4211-b951-dd282baaaec8"
                },
                {
                  "group": "right",
                  "id": "3efd3554-e3b0-460a-93bd-34c139e7749e"
                },
                {
                  "group": "bottom",
                  "id": "65a270f2-d934-4078-98be-37952422afa1"
                },
                {
                  "group": "left",
                  "id": "83e5645c-afe5-440c-800f-293cec4d911d"
                }
              ]
            },
            "id": "6294f2d1-4814-47e1-b98a-1e455d858b95",
            "data": {
              "type": "tm.Actor",
              "name": "Nurse",
              "description": "",
              "isTrustBoundary": false,
              "outOfScope": false,
              "reasonOutOfScope": "",
              "hasOpenThreats": true,
              "providesAuthentication": false,
              "threats": [
                {
                  "id": "4748e88c-f85b-4ba1-8f4b-1119e8ba5b02",
                  "title": "Akun Perawat disalahgunakan",
                  "status": "Mitigated",
                  "severity": "High",
                  "type": "Spoofing",
                  "description": "Data SOAP salah",
                  "mitigation": "Penggunaan sistem secara lokal, memperkuat akses lokal, Session Control",
                  "modelType": "STRIDE",
                  "new": false,
                  "number": 22,
                  "score": "16"
                },
                {
                  "id": "61eb38d6-8f71-4e0d-ac37-d6f2fe85eb8f",
                  "title": "Penyangkalan input data sOAP",
                  "status": "Open",
                  "severity": "Medium",
                  "type": "Repudiation",
                  "description": "Audit tidak valid",
                  "mitigation": "Immutable audit log",
                  "modelType": "STRIDE",
                  "new": false,
                  "number": 23,
                  "score": "9"
                }
              ],
              "threatFrequency": {
                "spoofing": 2,
                "repudiation": 2
              }
            },
            "zIndex": 11
          }
        ]
      }
    ],
    "diagramTop": 2,
    "reviewer": "Faris Aryaputra",
    "threatTop": 38
  }
}